tests/__init__.py
tests/__main__.py
tests/chinese_sentiment_cnn.py
tests/chinese_sentiment_rnn.py
tests/chinese_sentiment_rnn_attention.py
tests/test_fit.py
tests/test_number_y_fit.py
tests/test_predict_proba.py
tests/test_score_table.py
tests/test_series_x_fit.py
tests/thunews_rnn_attention.py
torch_text_classifier/__init__.py
torch_text_classifier/classifier_dataset.py
torch_text_classifier/encoder_cnn.py
torch_text_classifier/encoder_rnn.py
torch_text_classifier/encoder_rnn_attention.py
torch_text_classifier/text_classifier.py
torch_text_classifier/text_classifier_model.py
torch_text_classifier/torch_lm.py
torch_text_classifier/utils.py
torch_text_classifier/version.txt
torch_text_classifier/word_orders.json
torch_text_classifier-0.0.58.dist-info/LICENSE
torch_text_classifier-0.0.58.dist-info/METADATA
torch_text_classifier-0.0.58.dist-info/WHEEL
torch_text_classifier-0.0.58.dist-info/top_level.txt
torch_text_classifier-0.0.58.dist-info/RECORD
