Metadata-Version: 2.1
Name: torch-text-classifier
Version: 0.0.58
Summary: NLP tool
Home-page: https://github.com/infinity-future/torch-text-classifier
Author: infinityfuture
Author-email: infinityfuture@foxmail.com
License: MIT Licence
Keywords: pip,pytorch,classifier
Platform: any
Requires-Dist: torch
Requires-Dist: tqdm
Requires-Dist: scikit-learn
Requires-Dist: numpy
Requires-Dist: scipy
Requires-Dist: pypinyin
